{
    "message": "",
    "error": "",
    "status": 200,
    "time": 1681975604545,
    "timef": "2023-04-20T15:26:44.54554891+08:00",
    "head": {
        "url": "",
        "namespace": "",
        "doctype": ""
    },
    "sources": [],
    "packages": [],
    "mediae": [],
    "executables": [
        {
            "id": 2,
            "urn": "urn:executable:default#nautilus",
            "uuid": "ef03d54f-dea8-e333-1b39-e764d0b2e945",
            "created_at": 1681968403116,
            "updated_at": 1681968403116,
            "referer": "",
            "installation": 0,
            "name": "nautilus",
            "aliases": "nautilus,",
            "namespace": "default",
            "title": "Nautilus 文件",
            "description": "Nautilus 文件管理器",
            "icon": "/media/image/png/ca8eefedfab7179a13e12b5944ff032d576ea528e3165e2c0c7507df8798af69/explorer.png",
            "sha256sum": "260e0e6c1da0a30da0a02e912c1e9f3014e9af0f210b5906d5ff34da291fc0cf",
            "remark": "",
            "size": 1709488,
            "ready": false,
            "group": "",
            "state": "ready",
            "tags": "",
            "open_with_priority": 5,
            "os": "linux",
            "arch": "any",
            "version": "",
            "path": "/usr/bin/nautilus",
            "location_class": "executable",
            "location": 2
        }
    ],
    "contenttypes": [],
    "intenttemplates": [
        {
            "id": 4,
            "uuid": "636eaa9a-21cb-70d0-b412-bb8acb6a800f",
            "created_at": 1681969442606,
            "updated_at": 1681972074643,
            "referer": "",
            "installation": 0,
            "name": "open_worktree_with_nautilus",
            "icon": "/media/image/png/ca8eefedfab7179a13e12b5944ff032d576ea528e3165e2c0c7507df8798af69/explorer.png",
            "title": "用 nautilus 打开 git 工作区",
            "group": "nautilus",
            "description": "用 nautilus 打开 git 工作区",
            "method": "open",
            "target": "worktree",
            "type": "*",
            "with": "urn:executable:default#nautilus",
            "selector": ".open(worktree).as(*).with(urn:executable:default#nautilus)",
            "want_properties": null,
            "command": "${executable.path}",
            "args": "./",
            "env": "",
            "wd": "${worktree.dot-git-path}/.."
        },
        {
            "id": 3,
            "uuid": "bb2f8489-bab8-8a02-197f-c2b1fb43942b",
            "created_at": 1681969401061,
            "updated_at": 1681972010396,
            "referer": "",
            "installation": 0,
            "name": "open_submodule_with_nautilus",
            "icon": "/media/image/png/ca8eefedfab7179a13e12b5944ff032d576ea528e3165e2c0c7507df8798af69/explorer.png",
            "title": "用 nautilus 打开 git 子模块",
            "group": "nautilus",
            "description": "用 nautilus 打开 git 子模块",
            "method": "open",
            "target": "submodule",
            "type": "*",
            "with": "urn:executable:default#nautilus",
            "selector": ".open(submodule).as(*).with(urn:executable:default#nautilus)",
            "want_properties": null,
            "command": "${executable.path}",
            "args": "./",
            "env": "",
            "wd": "${submodule.dotgit}/.."
        },
        {
            "id": 6,
            "uuid": "ba59efaa-83f0-e5c4-1e48-9010ec724328",
            "created_at": 1681969552356,
            "updated_at": 1681971897202,
            "referer": "",
            "installation": 0,
            "name": "open_file_with_nautilus",
            "icon": "/media/image/png/ca8eefedfab7179a13e12b5944ff032d576ea528e3165e2c0c7507df8798af69/explorer.png",
            "title": "用 nautilus 打开文件",
            "group": "nautilus",
            "description": "用 nautilus 打开文件",
            "method": "open",
            "target": "file",
            "type": "*",
            "with": "urn:executable:default#nautilus",
            "selector": ".open(file).as(*).with(urn:executable:default#nautilus)",
            "want_properties": null,
            "command": "${executable.path}",
            "args": "./",
            "env": "",
            "wd": "${file.path}/.."
        },
        {
            "id": 7,
            "uuid": "887c306a-5553-b7f5-488d-3c6b9543fe79",
            "created_at": 1681969662839,
            "updated_at": 1681971822640,
            "referer": "",
            "installation": 0,
            "name": "open_project_with_nautilus",
            "icon": "/media/image/png/ca8eefedfab7179a13e12b5944ff032d576ea528e3165e2c0c7507df8798af69/explorer.png",
            "title": "用 nautilus 打开工程项目",
            "group": "nautilus",
            "description": "用 nautilus 打开工程项目",
            "method": "open",
            "target": "project",
            "type": "*",
            "with": "urn:executable:default#nautilus",
            "selector": ".open(project).as(*).with(urn:executable:default#nautilus)",
            "want_properties": null,
            "command": "${executable.path}",
            "args": "./",
            "env": "",
            "wd": "${project.fullpath}/.."
        },
        {
            "id": 5,
            "uuid": "e96d359b-ebcf-f407-cc37-fc433c33eb11",
            "created_at": 1681969523975,
            "updated_at": 1681971680565,
            "referer": "",
            "installation": 0,
            "name": "open_dir_with_nautilus",
            "icon": "/media/image/png/ca8eefedfab7179a13e12b5944ff032d576ea528e3165e2c0c7507df8798af69/explorer.png",
            "title": "用 nautilus 打开文件夹",
            "group": "nautilus",
            "description": "用 nautilus 打开文件夹",
            "method": "open",
            "target": "folder",
            "type": "*",
            "with": "urn:executable:default#nautilus",
            "selector": ".open(folder).as(*).with(urn:executable:default#nautilus)",
            "want_properties": null,
            "command": "${executable.path}",
            "args": "./",
            "env": "",
            "wd": "${folder.path}"
        },
        {
            "id": 2,
            "uuid": "79dc4b17-acb8-ec2e-c7de-b52136bbaaf8",
            "created_at": 1681969130426,
            "updated_at": 1681969269733,
            "referer": "",
            "installation": 0,
            "name": "open_repository_with_nautilus",
            "icon": "/media/image/png/ca8eefedfab7179a13e12b5944ff032d576ea528e3165e2c0c7507df8798af69/explorer.png",
            "title": "用 nautilus 打开 git 仓库",
            "group": "nautilus",
            "description": "用 nautilus 打开 git 仓库",
            "method": "open",
            "target": "repository",
            "type": "*",
            "with": "urn:executable:default#nautilus",
            "selector": ".open(repository).as(*).with(urn:executable:default#nautilus)",
            "want_properties": null,
            "command": "${executable.path}",
            "args": "./",
            "env": "",
            "wd": "${repository.wkdir}"
        }
    ]
}